{
    "name":"PresideCMS Extension: Foxy E-Commerce",
    "type":"preside-extensions",
    "version":"1.0.5",
    "location":"https://github.com/sebduggan/preside-ext-foxy/archive/v1.0.5.zip",
    "author":"Seb Duggan",
    "directory":"application/extensions",
    "homepage":"https://github.com/sebduggan/preside-ext-foxy",
    "documentation":"https://github.com/sebduggan/preside-ext-foxy/wiki",
    "repository":{
        "type":"git",
        "URL":"https://github.com/sebduggan/preside-ext-foxy"
    },
    "bugs":"https://github.com/sebduggan/preside-ext-foxy/issues",
    "slug":"preside-ext-foxy",
    "projectURL":"",
    "ignore":[
        ".git/*",
        ".gitignore",
        ".travis.yml",
        ".twgit_features_subject",
        "*.sh",
        "docs"
    ]
}